sc3s/__init__.py
sc3s/_cluster.py
sc3s/_consensus.py
sc3s/_legacy.py
sc3s/_misc.py
sc3s/tools.py
sc3s-0.1.1.dist-info/LICENSE
sc3s-0.1.1.dist-info/METADATA
sc3s-0.1.1.dist-info/WHEEL
sc3s-0.1.1.dist-info/top_level.txt
sc3s-0.1.1.dist-info/RECORD
