Metadata-Version: 2.1
Name: sc3s
Version: 0.1.1
Summary: Python Single Cell Consensus Clustering
Home-page: https://github.com/pittachalk/sc3s
Author: F.X. Quah
Author-email: fxq20@cam.ac.uk
License: UNKNOWN
Platform: UNKNOWN
Classifier: Programming Language :: Python :: 3
Classifier: License :: OSI Approved :: BSD License
Classifier: Operating System :: OS Independent
Requires-Python: >=3.6
Requires-Dist: numpy (<2,>=1.19.2)
Requires-Dist: pandas (>=1.1.5)
Requires-Dist: scikit-learn (>=0.23.2)
Requires-Dist: scanpy (>=1.7.0)
Requires-Dist: six (>=1.15.0)
Requires-Dist: setuptools (>=52.0.0)
Requires-Dist: joblib (>=1.0.0)
Requires-Dist: h5py (>=3.1.0)
Requires-Dist: seaborn
Requires-Dist: scipy
Requires-Dist: python-dateutil (>=2.8.1)
